[{"team_id": "105521408363571548", "team_code": "IHG", "team_name": "Illuminar Gaming", "rank": 0, "matches": 0, "elo": 0, "league": "UNKNOWN"}, {"team_id": "105521419784127190", "team_code": "KNF", "team_name": "Komil&Friends", "rank": 0, "matches": 0, "elo": 0, "league": "UNKNOWN"}, {"team_id": "109539776003058530", "team_code": "AB", "team_name": "Alior Bank Team", "rank": 0, "matches": 0, "elo": 0, "league": "UNKNOWN"}, {"team_id": "107416342401528388", "team_code": "MFSK", "team_name": "Maturalni Forsaken", "rank": 0, "matches": 0, "elo": 0, "league": "UNKNOWN"}, {"team_id": "105521412995449549", "team_code": "ESCA", "team_name": "Team ESCA Gaming", "rank": 0, "matches": 0, "elo": 0, "league": "UNKNOWN"}, {"team_id": "104710682193583854", "team_code": "WOLF", "team_name": "Topo Centras Iron Wolves", "rank": 0, "matches": 0, "elo": 0, "league": "UNKNOWN"}, {"team_id": "105553606349477427", "team_code": "Z10", "team_name": "Zero Tenacity", "rank": 0, "matches": 0, "elo": 0, "league": "UNKNOWN"}, {"team_id": "107599485973747723", "team_code": "GRP", "team_name": "Grypciocraft Esports", "rank": 0, "matches": 0, "elo": 0, "league": "UNKNOWN"}, {"team_id": "109539873500788632", "team_code": "EXD", "team_name": "EXEED", "rank": 0, "matches": 0, "elo": 0, "league": "UNKNOWN"}, {"team_id": "109800832177252614", "team_code": "OAE", "team_name": "Orbit Anonymo", "rank": 0, "matches": 0, "elo": 0, "league": "UNKNOWN"}]