[{"team_id": "109671201259007744", "team_code": "TLF", "team_name": "Team Liquid Honda First", "rank": 0, "matches": 0, "elo": 0, "league": "UNKNOWN"}, {"team_id": "106857761435870473", "team_code": "SN", "team_name": "Supernova", "rank": 0, "matches": 0, "elo": 0, "league": "UNKNOWN"}, {"team_id": "109783023470714128", "team_code": "TONY", "team_name": "Team Tony Top", "rank": 0, "matches": 0, "elo": 0, "league": "UNKNOWN"}, {"team_id": "102141671183409133", "team_code": "MU", "team_name": "Maryville University", "rank": 0, "matches": 0, "elo": 0, "league": "UNKNOWN"}, {"team_id": "106857734387052095", "team_code": "AOE", "team_name": "AOE Gold", "rank": 0, "matches": 0, "elo": 0, "league": "UNKNOWN"}, {"team_id": "108361563004344389", "team_code": "LAST", "team_name": "The Last Dance", "rank": 0, "matches": 0, "elo": 0, "league": "UNKNOWN"}, {"team_id": "108361575122450254", "team_code": "TACO", "team_name": "Team Fish Taco", "rank": 0, "matches": 0, "elo": 0, "league": "UNKNOWN"}, {"team_id": "109671193729027761", "team_code": "FLYF", "team_name": "FLY FAM", "rank": 0, "matches": 0, "elo": 0, "league": "UNKNOWN"}]