[{"team_id": "105521706535388095", "team_code": "ANO", "team_name": "Anorthosis Famagusta Esports", "rank": 0, "matches": 0, "elo": 0, "league": "UNKNOWN"}, {"team_id": "109696126554266494", "team_code": "GK", "team_name": "Geekay Esports", "rank": 0, "matches": 0, "elo": 0, "league": "UNKNOWN"}, {"team_id": "102787200129022886", "team_code": "ESB", "team_name": "eSuba", "rank": 0, "matches": 0, "elo": 0, "league": "UNKNOWN"}, {"team_id": "105504044166670507", "team_code": "USE", "team_name": "Unicorns of Love Sexy Edition", "rank": 0, "matches": 0, "elo": 0, "league": "UNKNOWN"}, {"team_id": "107467803833323099", "team_code": "HRTS", "team_name": "Los Heretics", "rank": 0, "matches": 0, "elo": 0, "league": "UNKNOWN"}, {"team_id": "105536918475957734", "team_code": "MCK", "team_name": "Macko Esports", "rank": 0, "matches": 0, "elo": 0, "league": "UNKNOWN"}, {"team_id": "103877625775457850", "team_code": "MRS", "team_name": "Movistar Riders", "rank": 0, "matches": 0, "elo": 0, "league": "UNKNOWN"}, {"team_id": "103935468920814040", "team_code": "GO", "team_name": "Team GO", "rank": 0, "matches": 0, "elo": 0, "league": "UNKNOWN"}, {"team_id": "104710354840711661", "team_code": "RDL", "team_name": "Riddle Esports", "rank": 0, "matches": 0, "elo": 0, "league": "UNKNOWN"}, {"team_id": "109523293035238887", "team_code": "AEG", "team_name": "Aegis", "rank": 0, "matches": 0, "elo": 0, "league": "UNKNOWN"}, {"team_id": "105553606349477427", "team_code": "Z10", "team_name": "Zero Tenacity", "rank": 0, "matches": 0, "elo": 0, "league": "UNKNOWN"}, {"team_id": "103877675241047720", "team_code": "LDLC", "team_name": "LDLC OL", "rank": 0, "matches": 0, "elo": 0, "league": "UNKNOWN"}, {"team_id": "102235771678061291", "team_code": "IW", "team_name": "DenizBank \u00c4\u00b0stanbul Wildcats", "rank": 0, "matches": 0, "elo": 0, "league": "UNKNOWN"}, {"team_id": "109800832177252614", "team_code": "OAE", "team_name": "Orbit Anonymo", "rank": 0, "matches": 0, "elo": 0, "league": "UNKNOWN"}, {"team_id": "109669678317817381", "team_code": "FUT", "team_name": "FUT ESPORTS", "rank": 0, "matches": 0, "elo": 0, "league": "UNKNOWN"}, {"team_id": "105559480124455983", "team_code": "SKP", "team_name": "SK Gaming Prime", "rank": 0, "matches": 0, "elo": 0, "league": "UNKNOWN"}]